pymyami/__init__.py
pymyami/approximate.py
pymyami/calculate.py
pymyami/helpers.py
pymyami/params.py
pymyami/pitzer.py
pymyami/parameters/Tab2.csv
pymyami/parameters/TabA1.csv
pymyami/parameters/TabA10.csv
pymyami/parameters/TabA11.csv
pymyami/parameters/TabA12.csv
pymyami/parameters/TabA2.csv
pymyami/parameters/TabA3.csv
pymyami/parameters/TabA4.csv
pymyami/parameters/TabA5.csv
pymyami/parameters/TabA6.csv
pymyami/parameters/TabA7.csv
pymyami/parameters/TabA8.csv
pymyami/parameters/TabA9.csv
pymyami/parameters/TabSpecial.csv
pymyami/parameters/Zeebe2019.csv
pymyami/parameters/gen_approx_coefs.py
pymyami/parameters/gen_params.py
pymyami/parameters/phi_bases.json
pymyami/parameters/pitzer_params.json
pymyami/parameters/seawater_correction_approximated.json
pymyami/parameters/standard_seawater.csv
pymyami/parameters/theta_bases.json
pymyami-2.1.1.dist-info/licenses/LICENSE
pymyami-2.1.1.dist-info/METADATA
pymyami-2.1.1.dist-info/WHEEL
pymyami-2.1.1.dist-info/top_level.txt
pymyami-2.1.1.dist-info/zip-safe
pymyami-2.1.1.dist-info/RECORD
