Metadata-Version: 2.4
Name: pymyami
Version: 2.1.1
Summary: MyAMI specific ion interaction model for calculating stoichiometric equilibrium constants in modified seawater.
Author-email: Oscar Branson <ob266@cam.ac.uk>
Maintainer-email: Ross Whiteford <Ross.Whiteford@rhul.ac.uk>
License-Expression: MIT
Project-URL: Homepage, https://github.com/PalaeoCarbonateChemistry/pymyami
Project-URL: PalaeoCarbonateChemistry, https://github.com/PalaeoCarbonateChemistry
Classifier: Programming Language :: Python :: 3
Requires-Python: >=3.9
License-File: LICENSE
Requires-Dist: numpy
Requires-Dist: pandas
Requires-Dist: matplotlib
Requires-Dist: scikit-learn
Requires-Dist: scipy
Dynamic: license-file
